bluet/__about__.py
bluet/__init__.py
bluet/central.py
bluet/peripheral.py
bluet/process.py
bluet/process_zephyr.py
bluet/py.typed
bluet/tester_device.py
bluet-0.0.4.dist-info/METADATA
bluet-0.0.4.dist-info/WHEEL
bluet-0.0.4.dist-info/licenses/LICENSE
bluet-0.0.4.dist-info/RECORD
