Metadata-Version: 2.3
Name: bluet
Version: 0.0.4
Summary: A unit-test library and setup for embedded bluetooth testing.
Project-URL: Issues, https://github.com/jeru/bluet/issues
Project-URL: Source, https://github.com/jeru/bluet
Author-email: Cheng Sheng <jeru.sheng@gmail.com>
License-Expression: Apache-2.0
License-File: LICENSE
Keywords: ble,bluetooth,mock,test,unit-test
Classifier: Development Status :: 4 - Beta
Classifier: Programming Language :: Python
Classifier: Programming Language :: Python :: 3.9
Classifier: Programming Language :: Python :: 3.10
Classifier: Programming Language :: Python :: 3.11
Classifier: Programming Language :: Python :: 3.12
Classifier: Programming Language :: Python :: Implementation :: CPython
Classifier: Programming Language :: Python :: Implementation :: PyPy
Requires-Python: >=3.9
Requires-Dist: bumble>=0.0.190
